anna_lib/__init__.py
anna_lib/selenium/__init__.py
anna_lib/selenium/assertions.py
anna_lib/selenium/driver.py
anna_lib/selenium/event_executor.py
anna_lib/selenium/events.py
anna_lib/selenium/util.py
anna_lib/task/__init__.py
anna_lib/task/abstract_task.py
anna_lib/task/factory.py
anna_lib-0.0.13.dist-info/METADATA
anna_lib-0.0.13.dist-info/WHEEL
anna_lib-0.0.13.dist-info/top_level.txt
anna_lib-0.0.13.dist-info/RECORD
