Metadata-Version: 2.1
Name: anna-lib
Version: 0.0.13
Summary: selenium interface
Home-page: https://github.com/patrikpihlstrom/anna-lib
Author: Patrik Pihlstrom
Author-email: patrik.pihlstrom@gmail.com
License: UNKNOWN
Platform: UNKNOWN
Requires-Dist: selenium
